q8s/__init__.py
q8s/__main__.py
q8s/bakefile.py
q8s/cli.py
q8s/constants.py
q8s/enums.py
q8s/execution.py
q8s/install.py
q8s/kernel.py
q8s/multifiles.py
q8s/project.py
q8s/utils.py
q8s/workload.py
q8s/matplotlib/backend.py
q8s/plugins/__init__.py
q8s/plugins/cpu_job.py
q8s/plugins/cuda_job.py
q8s/plugins/job.py
q8s/plugins/job_template_spec.py
q8s/plugins/utils/__init__.py
q8s/plugins/utils/git_info.py
q8s-0.11.2.dist-info/licenses/LICENSE
q8s-0.11.2.dist-info/METADATA
q8s-0.11.2.dist-info/WHEEL
q8s-0.11.2.dist-info/entry_points.txt
q8s-0.11.2.dist-info/top_level.txt
q8s-0.11.2.dist-info/RECORD
