Metadata-Version: 2.4
Name: q8s
Version: 0.11.2
Summary: Kernel extension for executing quantum programs in simulators on q8s clusters
Author-email: Vlad Stirbu <vstirbu@gmail.com>
License:                                  Apache License
Project-URL: Homepage, https://github.com/qubernetes-dev/q8s-kernel
Project-URL: Issues, https://github.com/qubernetes-dev/q8s-kernel/issues
Keywords: jupyter,quantum,kernel
Classifier: Development Status :: 4 - Beta
Classifier: Intended Audience :: Developers
Classifier: Programming Language :: Python :: 3
Classifier: Programming Language :: Python :: 3.10
Classifier: Programming Language :: Python :: 3.11
Classifier: Programming Language :: Python :: 3.12
Classifier: Programming Language :: Python :: 3.13
Classifier: License :: OSI Approved :: MIT License
Classifier: Operating System :: OS Independent
Requires-Python: >=3.10
License-File: LICENSE
Requires-Dist: dacite==1.9.2
Requires-Dist: ipykernel==6.26.0
Requires-Dist: kubernetes==29.0.0
Requires-Dist: matplotlib==3.10.1
Requires-Dist: pluggy==1.5.0
Requires-Dist: python-dotenv==1.0.1
Requires-Dist: pyyaml==6.0.2
Requires-Dist: typer>=0.15.4
Requires-Dist: GitPython>=3.1.43
Requires-Dist: python-dxf>=12.1.1
Provides-Extra: benchmark
Requires-Dist: pandas; extra == "benchmark"
Requires-Dist: testbook; extra == "benchmark"
Requires-Dist: mlflow; extra == "benchmark"
Provides-Extra: development
Requires-Dist: pyre-check; extra == "development"
Requires-Dist: pre-commit; extra == "development"
Requires-Dist: pytest; extra == "development"
Requires-Dist: pytest-cov; extra == "development"
Requires-Dist: dockerfile-parse; extra == "development"
Dynamic: license-file
